qt5reactor/__init__.py
qt5reactor/_version.py
qt5reactor/core.py
qt5reactor/tests/__init__.py
qt5reactor/tests/test_core.py
qt5reactor-0.6.3.dist-info/LICENSE
qt5reactor-0.6.3.dist-info/METADATA
qt5reactor-0.6.3.dist-info/WHEEL
qt5reactor-0.6.3.dist-info/top_level.txt
qt5reactor-0.6.3.dist-info/RECORD
