Metadata-Version: 2.1
Name: qt5reactor
Version: 0.6.3
Summary: Twisted Qt Integration
Home-page: https://github.com/twisted/qt5reactor
Author: Christopher R. Wood
Author-email: chris@leastauthority.com
License: MIT
Keywords: Qt,twisted
Platform: UNKNOWN
Classifier: Development Status :: 5 - Production/Stable
Classifier: Environment :: X11 Applications :: Qt
Classifier: Framework :: Twisted
Classifier: Intended Audience :: Developers
Classifier: License :: OSI Approved :: MIT License
Classifier: Operating System :: OS Independent
Classifier: Programming Language :: Python
Classifier: Programming Language :: Python :: 3
Classifier: Programming Language :: Python :: 3.5
Classifier: Programming Language :: Python :: 3.6
Classifier: Programming Language :: Python :: 3.7
Classifier: Natural Language :: English
Classifier: Topic :: Software Development :: Libraries :: Python Modules
Requires-Python: >=3.5
Provides-Extra: pyqt5
Provides-Extra: pyside2
Provides-Extra: test
